Metadata-Version: 2.1
Name: pandorinha
Version: 0.0.1a2
Summary: discover music
Home-page: https://github.com/OpenJarbas/pandorinha
Author: JarbasAi
License: UNKNOWN
Platform: UNKNOWN
